pypcaptools/Flow.py
pypcaptools/Packet.py
pypcaptools/__init__.py
pypcaptools/pcaphandler.py
pypcaptools/pcaptodatabasehandler.py
pypcaptools/util.py
pypcaptools/TrafficDB/FlowDB.py
pypcaptools/TrafficDB/ResourceDB.py
pypcaptools/TrafficDB/TraceDB.py
pypcaptools/TrafficDB/TrafficDB.py
pypcaptools/TrafficDB/__init__.py
pypcaptools/TrafficInfo/FlowInfo.py
pypcaptools/TrafficInfo/ResourceInfo.py
pypcaptools/TrafficInfo/TraceInfo.py
pypcaptools/TrafficInfo/TrafficInfo.py
pypcaptools/TrafficInfo/__init__.py
pypcaptools-2.4.dist-info/licenses/LICENSE
pypcaptools-2.4.dist-info/METADATA
pypcaptools-2.4.dist-info/WHEEL
pypcaptools-2.4.dist-info/top_level.txt
pypcaptools-2.4.dist-info/RECORD
