Metadata-Version: 2.4
Name: pypcaptools
Version: 2.4
Summary: 一个用于解析pcap文件的python库
Home-page: https://github.com/aimafan123/pypcaptools.git
Author: aimafan123
Author-email: chongrufan@nuaa.edu.cn
Classifier: Programming Language :: Python :: 3
Classifier: License :: OSI Approved :: MIT License
Requires-Python: >=3.8
License-File: LICENSE
Requires-Dist: dpkt==1.9.8
Requires-Dist: scapy==2.6.0
Requires-Dist: mysql-connector-python==9.1.0
Dynamic: author
Dynamic: author-email
Dynamic: classifier
Dynamic: description
Dynamic: description-content-type
Dynamic: home-page
Dynamic: license-file
Dynamic: requires-dist
Dynamic: requires-python
Dynamic: summary
